ambulance_game/__init__.py
ambulance_game/comparisons.py
ambulance_game/game.py
ambulance_game/queue.py
ambulance_game/markov/__init__.py
ambulance_game/markov/blocking.py
ambulance_game/markov/graphical.py
ambulance_game/markov/markov.py
ambulance_game/markov/proportion.py
ambulance_game/markov/tikz.py
ambulance_game/markov/utils.py
ambulance_game/markov/waiting.py
ambulance_game/simulation/__init__.py
ambulance_game/simulation/dists.py
ambulance_game/simulation/simulation.py
ambulance_game-0.0.7.dist-info/LICENSE
ambulance_game-0.0.7.dist-info/WHEEL
ambulance_game-0.0.7.dist-info/METADATA
ambulance_game-0.0.7.dist-info/RECORD
