Metadata-Version: 2.1
Name: ambulance_game
Version: 0.0.7
Summary: A library to study the gaming that takes place at the interface of hospitals
Home-page: https://github.com/11michalis11/AmbulanceDecisionGame
Author: Michalis Panayides
Author-email: PanayidesM@cardiff.ac.uk
Requires-Python: >=3.8
Classifier: License :: OSI Approved :: MIT License
Requires-Dist: ciw==2.2.3
Requires-Dist: dask>=2021.08.1, <2021.09.0
Requires-Dist: matplotlib>=3.4.3, <3.5
Requires-Dist: nashpy==0.0.23
Requires-Dist: networkx>=2.4, <2.5
Requires-Dist: numpy>=1.20.0, <1.21.6
Requires-Dist: scipy>=1.7.1, <1.8
Requires-Dist: sympy>=1.5.1, <1.6
